pymumble_py3/__init__.py
pymumble_py3/blobs.py
pymumble_py3/callbacks.py
pymumble_py3/channels.py
pymumble_py3/commands.py
pymumble_py3/constants.py
pymumble_py3/errors.py
pymumble_py3/messages.py
pymumble_py3/mumble.py
pymumble_py3/mumble_pb2.py
pymumble_py3/soundoutput.py
pymumble_py3/soundqueue.py
pymumble_py3/tools.py
pymumble_py3/users.py
pymumble-1.2.dist-info/LICENSE
pymumble-1.2.dist-info/METADATA
pymumble-1.2.dist-info/WHEEL
pymumble-1.2.dist-info/top_level.txt
pymumble-1.2.dist-info/RECORD
