Metadata-Version: 2.1
Name: pymumble
Version: 1.2
Summary: Mumble library used for multiple uses like making mumble bot.
Home-page: https://github.com/azlux/pymumble
Author: Azlux
Author-email: github@azlux.fr
License: GPLv3
Platform: UNKNOWN
Classifier: Programming Language :: Python :: 3
Classifier: License :: OSI Approved :: GNU General Public License v3 (GPLv3)
Classifier: Operating System :: OS Independent
Requires-Python: >=3.6
Requires-Dist: opuslib (==2.0.0)
Requires-Dist: protobuf (==3.4.0)
